edd_tool/__init__.py
edd_tool/cli.py
edd_tool/data/__init__.py
edd_tool/data/edd-tool.rc.template
edd_tool-0.2.3.dist-info/licenses/LICENSE
edd_tool-0.2.3.dist-info/METADATA
edd_tool-0.2.3.dist-info/WHEEL
edd_tool-0.2.3.dist-info/entry_points.txt
edd_tool-0.2.3.dist-info/top_level.txt
edd_tool-0.2.3.dist-info/RECORD
