Metadata-Version: 2.4
Name: edd-tool
Version: 0.2.3
Summary: EDD deployment and plugin management tool
Author-email: Ewan Barr <ebarr@mpifr-bonn.mpg.de>
License: Copyright 2025 Ewan Barr
Project-URL: Homepage, https://gitlab.mpcdf.mpg.de/mpifr-bdg/edd_installer
Project-URL: Documentation, https://gitlab.mpcdf.mpg.de/mpifr-bdg/edd_installer
Project-URL: Repository, https://gitlab.mpcdf.mpg.de/mpifr-bdg/edd_installer.git
Project-URL: Bug Tracker, https://gitlab.mpcdf.mpg.de/mpifr-bdg/edd_installer/issues
Requires-Python: >=3.11
License-File: LICENSE
Requires-Dist: ansible>=12.0.0
Requires-Dist: requests
Dynamic: license-file
